orpheus_collage_tools/__init__.py
orpheus_collage_tools/cli.py
orpheus_collage_tools/core.py
orpheus_collage_tools/lib/download_album_preferences.py
orpheus_collage_tools/lib/download_collage_torrents.py
orpheus_collage_tools/lib/download_crate.py
orpheus_collage_tools/lib/find_album_collages.py
orpheus_collage_tools/lib/search_artist_collages.py
orpheus_collage_tools/lib/search_collages.py
orpheus_collage_tools/lib/__pycache__/download_album_preferences.cpython-313.pyc
orpheus_collage_tools/lib/__pycache__/download_collage_torrents.cpython-313.pyc
orpheus_collage_tools/lib/__pycache__/download_crate.cpython-313.pyc
orpheus_collage_tools/lib/__pycache__/find_album_collages.cpython-313.pyc
orpheus_collage_tools/scripts/macos/collage_tools.sh
orpheus_collage_tools/scripts/windows/orpheus.bat
orpheus_collage_tools-1.0.0.dist-info/licenses/LICENSE
orpheus_collage_tools-1.0.0.dist-info/METADATA
orpheus_collage_tools-1.0.0.dist-info/WHEEL
orpheus_collage_tools-1.0.0.dist-info/entry_points.txt
orpheus_collage_tools-1.0.0.dist-info/top_level.txt
orpheus_collage_tools-1.0.0.dist-info/RECORD
