Metadata-Version: 2.4
Name: orpheus-collage-tools
Version: 1.0.0
Summary: Cross-platform Orpheus Collage Tools for music discovery and downloading
License-Expression: MIT
Project-URL: Homepage, https://pypi.org/project/orpheus-collage-tools/
Project-URL: Repository, https://github.com/cameronbrooks/orpheus-collage-tools
Project-URL: Issues, https://github.com/cameronbrooks/orpheus-collage-tools/issues
Classifier: Development Status :: 4 - Beta
Classifier: Intended Audience :: End Users/Desktop
Classifier: Operating System :: OS Independent
Classifier: Programming Language :: Python :: 3
Classifier: Programming Language :: Python :: 3.8
Classifier: Programming Language :: Python :: 3.9
Classifier: Programming Language :: Python :: 3.10
Classifier: Programming Language :: Python :: 3.11
Classifier: Programming Language :: Python :: 3.12
Classifier: Topic :: Multimedia :: Sound/Audio
Requires-Python: >=3.8
License-File: LICENSE
Requires-Dist: aiohttp>=3.8.0
Requires-Dist: beautifulsoup4>=4.11.0
Requires-Dist: requests>=2.28.0
Dynamic: license-file
